{"name":"Mnhaon","body":"## PROJECT TITLE:  \r\nmnhaon\r\n\r\n## PURPOSE OF PROJECT: \r\nTo teach my kid how to code and share that code:\r\n\r\nThe constraints that we will try to follow...\r\n- The source must be shared via github and in a compiled playable format with in two weeks.\r\n- The focus will be on creating, experiencing and sharing code not the framework or deep syntax itself (so we will be using greenfoot, gosu or something like them).\r\n- The two students will write all of the code using XP and scrum with an occasional booster script from me\r\n- The two students provide all of the content: music, graphics, story and code\r\n- We will have fun\r\n\r\n## VERSION or DATE:  \r\n09/19/2011\r\n\r\n## HOW TO START THIS PROJECT:  \r\nInstall green foot from greenfoot.org (needs java)\r\n\r\n## AUTHORS:  \r\nCaden Floyd, Jonah Floyd\r\n\r\n## USER INSTRUCTIONS:  \r\nn/a\r\n\r\nMore information: http://archcoder.com/articles/20110915/kid-gamification-planning\r\nSubscribe to the project: http://archcoder.com/taxonomy/term/8/0/feed\r\n\r\n","tagline":"The epic journey of a family of turtles just trying to get home","google":"","note":"Don't delete this file! It's used internally to help with page regeneration."}